apsapi/__init__.py
apsapi/aps.py
apsapi/aps_api.py
apsapi/aps_exceptions.py
apsapi/aps_requests.py
apsapi/aps_utils.py
vmx_aps-2.7.0.dist-info/licenses/LICENSE
vmx_aps-2.7.0.dist-info/METADATA
vmx_aps-2.7.0.dist-info/WHEEL
vmx_aps-2.7.0.dist-info/entry_points.txt
vmx_aps-2.7.0.dist-info/top_level.txt
vmx_aps-2.7.0.dist-info/RECORD
